pandas_vectors.py
pandas_vectors-0.1.1.dist-info/DESCRIPTION.rst
pandas_vectors-0.1.1.dist-info/METADATA
pandas_vectors-0.1.1.dist-info/RECORD
pandas_vectors-0.1.1.dist-info/WHEEL
pandas_vectors-0.1.1.dist-info/metadata.json
pandas_vectors-0.1.1.dist-info/top_level.txt
