Metadata-Version: 2.0
Name: pandas-vectors
Version: 0.1.1
Summary: convenience functions for dealing with vectors in panda dataframes
Home-page: https://github.com/richjoyce/pandas_vectors
Author: Richard Joyce
Author-email: rjoyce@ucdavis.edu
License: MIT
Platform: UNKNOWN
